{
  "updated": "2026-06-22T16:14:35.337365+00:00",
  "prices": {
    "AMZN": {
      "price": 233.35,
      "change": -9.6984,
      "changePct": -3.9903,
      "prevClose": 243.0484
    },
    "COIN": {
      "price": 166.12,
      "change": 2.92,
      "changePct": 1.7892,
      "prevClose": 163.2
    },
    "DIS": {
      "price": 102.3104,
      "change": -1.2806,
      "changePct": -1.2362,
      "prevClose": 103.591
    },
    "HODL": {
      "price": 18.28,
      "change": 0.4623,
      "changePct": 2.5946,
      "prevClose": 17.8177
    },
    "JOBY": {
      "price": 10.035,
      "change": 0.0963,
      "changePct": 0.9689,
      "prevClose": 9.9387
    },
    "MRNA": {
      "price": 59.89,
      "change": -4.1195,
      "changePct": -6.4358,
      "prevClose": 64.0095
    },
    "NET": {
      "price": 214.24,
      "change": -9.76,
      "changePct": -4.3571,
      "prevClose": 224.0
    },
    "NFLX": {
      "price": 72.59,
      "change": -4.7206,
      "changePct": -6.106,
      "prevClose": 77.3106
    },
    "NVDA": {
      "price": 209.645,
      "change": -0.685,
      "changePct": -0.3257,
      "prevClose": 210.33
    },
    "SNAP": {
      "price": 4.669,
      "change": -0.041,
      "changePct": -0.8705,
      "prevClose": 4.71
    },
    "TSLA": {
      "price": 408.39,
      "change": 9.66,
      "changePct": 2.4227,
      "prevClose": 398.73
    },
    "ZM": {
      "price": 83.445,
      "change": -2.9657,
      "changePct": -3.4321,
      "prevClose": 86.4107
    }
  }
}